ci_cd_tool/__init__.py
ci_cd_tool/cli.py
ci_cd_tool/analyzer/__init__.py
ci_cd_tool/analyzer/project_analyzer.py
ci_cd_tool/ci/__init__.py
ci_cd_tool/ci/base_ci.py
ci_cd_tool/ci/git_setting.py
ci_cd_tool/ci/github_actions.py
ci_cd_tool/ci/gitlab_ci.py
ci_cd_tool/ci/jenkins.py
ci_cd_tool/ci/template_manager.py
ci_cd_tool/commands/__init__.py
ci_cd_tool/commands/base.py
ci_cd_tool/commands/init_commands.py
ci_cd_tool/config/__init__.py
ci_cd_tool/config/base_config.py
ci_cd_tool/config/config_manager.py
ci_cd_tool/config/configuration.py
ci_cd_tool/config/environment.py
ci_cd_tool/core/container.py
ci_cd_tool/core/exceptions.py
ci_cd_tool/core/factory.py
ci_cd_tool/core/logging.py
ci_cd_tool/core/monitoring.py
ci_cd_tool/core/plugin.py
ci_cd_tool/core/test_config.py
ci_cd_tool/deploy/__init__.py
ci_cd_tool/deploy/aws_deployer.py
ci_cd_tool/deploy/base_deployer.py
ci_cd_tool/deploy/heroku_deployer.py
ci_cd_tool/templates/__init__.py
ci_cd_tool/templates/ci_generator.py
ci_cd_tool/templates/git_manager.py
ci_cd_tool/templates/template_content_generator.py
ci_cd_tool/templates/template_manager.py
ci_cd_tool/tests/__init__.py
ci_cd_tool/tests/test_example.py
ci_cd_tool/tests/fast/__init__.py
ci_cd_tool/tests/fast/fast_example.py
ci_cd_tool/utils/__init__.py
ci_cd_tool/utils/cli_prompt.py
ci_cd_tool-0.3.1.dist-info/METADATA
ci_cd_tool-0.3.1.dist-info/WHEEL
ci_cd_tool-0.3.1.dist-info/entry_points.txt
ci_cd_tool-0.3.1.dist-info/top_level.txt
ci_cd_tool-0.3.1.dist-info/RECORD
