Metadata-Version: 2.1
Name: ci_cd_tool
Version: 0.3.1
Summary: CI/CD 자동화 도구
Author-email: Your Name <your.email@example.com>
Classifier: Programming Language :: Python :: 3
Classifier: License :: OSI Approved :: MIT License
Classifier: Operating System :: OS Independent
Requires-Python: >=3.8
Requires-Dist: click>=8.1.7
Requires-Dist: rich>=13.7.0
Requires-Dist: dependency-injector>=4.41.0
Requires-Dist: pyyaml>=6.0.1
Requires-Dist: python-dotenv>=1.0.0
Requires-Dist: requests>=2.31.0
Requires-Dist: GitPython>=3.1.0
Requires-Dist: coverage>=7.4.0
Requires-Dist: pytest>=7.4.0
Requires-Dist: pytest-cov>=4.1.0
Requires-Dist: black>=23.12.0
Requires-Dist: isort>=5.13.0
Requires-Dist: flake8>=7.0.0
